verilator/vsrc/adder.v
module fullAdder (
    input A,
    input B,
    input Cin,
    output Sum,
    output Cout
);
    assign Sum = A ^ B ^ Cin;
    assign Cout = (A & B) | (B & Cin) | (A & Cin);
endmodule

module Adder (
    input [3:0] A,
    input [3:0] B,
    input Cin,
    output [3:0] Sum,
    output Cout
);
    wire Cout0, Cout1, Cout2;
  
    fullAdder FA0 (
        .A(A[0]),
        .B(B[0]),
        .Cin(Cin),
        .Sum(Sum[0]),
        .Cout(Cout0)
    );

    fullAdder FA1 (
        .A(A[1]),
        .B(B[1]),
        .Cin(Cout0),
        .Sum(Sum[1]),
        .Cout(Cout1)
    );

    fullAdder FA2 (
        .A(A[2]),
        .B(B[2]),
        .Cin(Cout1),
        .Sum(Sum[2]),
        .Cout(Cout2)
    );

    fullAdder FA3 (
        .A(A[3]),
        .B(B[3]),
        .Cin(Cout2),
        .Sum(Sum[3]),
        .Cout(Cout)
    );

endmodule

adder/build/wave.vcd
$version Generated by VerilatedVcd $end
$timescale 1s $end
 $scope module TOP $end
  $var wire 4 & A [3:0] $end
  $var wire 4 ' B [3:0] $end
  $var wire 1 ( Cin $end
  $var wire 4 ) Sum [3:0] $end
  $var wire 1 * Cout $end
  $scope module Adder $end
   $var wire 4 & A [3:0] $end
   $var wire 4 ' B [3:0] $end
   $var wire 1 ( Cin $end
   $var wire 4 ) Sum [3:0] $end
   $var wire 1 * Cout $end
   $var wire 1 # Cout0 $end
   $var wire 1 $ Cout1 $end
   $var wire 1 % Cout2 $end
   $scope module FA0 $end
    $var wire 1 + A $end
    $var wire 1 , B $end
    $var wire 1 ( Cin $end
    $var wire 1 - Sum $end
    $var wire 1 # Cout $end
   $upscope $end
   $scope module FA1 $end
    $var wire 1 . A $end
    $var wire 1 / B $end
    $var wire 1 # Cin $end
    $var wire 1 0 Sum $end
    $var wire 1 $ Cout $end
   $upscope $end
   $scope module FA2 $end
    $var wire 1 1 A $end
    $var wire 1 2 B $end
    $var wire 1 $ Cin $end
    $var wire 1 3 Sum $end
    $var wire 1 % Cout $end
   $upscope $end
   $scope module FA3 $end
    $var wire 1 4 A $end
    $var wire 1 5 B $end
    $var wire 1 % Cin $end
    $var wire 1 6 Sum $end
    $var wire 1 * Cout $end
   $upscope $end
  $upscope $end
 $upscope $end
$enddefinitions $end


#0
0#
0$
0%
b0000 &
b0000 '
0(
b0000 )
0*
0+
0,
0-
0.
0/
00
01
02
03
04
05
06
#1
1(
b0001 )
1-
#2
b0001 '
0(
1,
#3
1#
1(
b0010 )
0-
10
#4
0#
b0010 '
0(
0,
1/
#5
1(
b0011 )
1-
#6
b0011 '
0(
1,
#7
1#
1$
1(
b0100 )
0-
00
13
#8
0#
0$
b0100 '
0(
0,
0/
12
#9
1(
b0101 )
1-
#10
b0101 '
0(
1,
#11
1#
1(
b0110 )
0-
10
#12
0#
b0110 '
0(
0,
1/
#13
1(
b0111 )
1-
#14
b0111 '
0(
1,
#15
1#
1$
1%
1(
b1000 )
0-
00
03
16
#16
0#
0$
0%
b1000 '
0(
0,
0/
02
15
#17
1(
b1001 )
1-
#18
b1001 '
0(
1,
#19
1#
1(
b1010 )
0-
10
#20
0#
b1010 '
0(
0,
1/
#21
1(
b1011 )
1-
#22
b1011 '
0(
1,
#23
1#
1$
1(
b1100 )
0-
00
13
#24
0#
0$
b1100 '
0(
0,
0/
12
#25
1(
b1101 )
1-
#26
b1101 '
0(
1,
#27
1#
1(
b1110 )
0-
10
#28
0#
b1110 '
0(
0,
1/
#29
1(
b1111 )
1-
#30
b1111 '
0(
1,
#31
1#
1$
1%
1(
b0000 )
1*
0-
00
03
06
#32
0#
0$
0%
b0001 &
b0000 '
0(
b0001 )
0*
1+
0,
1-
0/
02
05
#33
1#
1(
b0010 )
0-
10
#34
b0001 '
0(
1,
#35
1(
b0011 )
1-
#36
0#
b0010 '
0(
0,
1/
#37
1#
1$
1(
b0100 )
0-
00
13
#38
b0011 '
0(
1,
#39
1(
b0101 )
1-
#40
0#
0$
b0100 '
0(
0,
0/
12
#41
1#
1(
b0110 )
0-
10
#42
b0101 '
0(
1,
#43
1(
b0111 )
1-
#44
0#
b0110 '
0(
0,
1/
#45
1#
1$
1%
1(
b1000 )
0-
00
03
16
#46
b0111 '
0(
1,
#47
1(
b1001 )
1-
#48
0#
0$
0%
b1000 '
0(
0,
0/
02
15
#49
1#
1(
b1010 )
0-
10
#50
b1001 '
0(
1,
#51
1(
b1011 )
1-
#52
0#
b1010 '
0(
0,
1/
#53
1#
1$
1(
b1100 )
0-
00
13
#54
b1011 '
0(
1,
#55
1(
b1101 )
1-
#56
0#
0$
b1100 '
0(
0,
0/
12
#57
1#
1(
b1110 )
0-
10
#58
b1101 '
0(
1,
#59
1(
b1111 )
1-
#60
0#
b1110 '
0(
0,
1/
#61
1#
1$
1%
1(
b0000 )
1*
0-
00
03
06
#62
b1111 '
0(
1,
#63
1(
b0001 )
1-
#64
0#
0$
0%
b0010 &
b0000 '
0(
b0010 )
0*
0+
0,
0-
1.
0/
10
02
05
#65
1(
b0011 )
1-
#66
b0001 '
0(
1,
#67
1#
1$
1(
b0100 )
0-
00
13
#68
0#
b0010 '
0(
0,
1/
#69
1(
b0101 )
1-
#70
b0011 '
0(
1,
#71
1#
1(
b0110 )
0-
10
#72
0#
0$
b0100 '
0(
0,
0/
12
#73
1(
b0111 )
1-
#74
b0101 '
0(
1,
#75
1#
1$
1%
1(
b1000 )
0-
00
03
16
#76
0#
b0110 '
0(
0,
1/
#77
1(
b1001 )
1-
#78
b0111 '
0(
1,
#79
1#
1(
b1010 )
0-
10
#80
0#
0$
0%
b1000 '
0(
0,
0/
02
15
#81
1(
b1011 )
1-
#82
b1001 '
0(
1,
#83
1#
1$
1(
b1100 )
0-
00
13
#84
0#
b1010 '
0(
0,
1/
#85
1(
b1101 )
1-
#86
b1011 '
0(
1,
#87
1#
1(
b1110 )
0-
10
#88
0#
0$
b1100 '
0(
0,
0/
12
#89
1(
b1111 )
1-
#90
b1101 '
0(
1,
#91
1#
1$
1%
1(
b0000 )
1*
0-
00
03
06
#92
0#
b1110 '
0(
0,
1/
#93
1(
b0001 )
1-
#94
b1111 '
0(
1,
#95
1#
1(
b0010 )
0-
10
#96
0#
0$
0%
b0011 &
b0000 '
0(
b0011 )
0*
1+
0,
1-
0/
02
05
#97
1#
1$
1(
b0100 )
0-
00
13
#98
b0001 '
0(
1,
#99
1(
b0101 )
1-
#100
0#
b0010 '
0(
0,
1/
#101
1#
1(
b0110 )
0-
10
#102
b0011 '
0(
1,
#103
1(
b0111 )
1-
#104
0#
0$
b0100 '
0(
0,
0/
12
#105
1#
1$
1%
1(
b1000 )
0-
00
03
16
#106
b0101 '
0(
1,
#107
1(
b1001 )
1-
#108
0#
b0110 '
0(
0,
1/
#109
1#
1(
b1010 )
0-
10
#110
b0111 '
0(
1,
#111
1(
b1011 )
1-
#112
0#
0$
0%
b1000 '
0(
0,
0/
02
15
#113
1#
1$
1(
b1100 )
0-
00
13
#114
b1001 '
0(
1,
#115
1(
b1101 )
1-
#116
0#
b1010 '
0(
0,
1/
#117
1#
1(
b1110 )
0-
10
#118
b1011 '
0(
1,
#119
1(
b1111 )
1-
#120
0#
0$
b1100 '
0(
0,
0/
12
#121
1#
1$
1%
1(
b0000 )
1*
0-
00
03
06
#122
b1101 '
0(
1,
#123
1(
b0001 )
1-
#124
0#
b1110 '
0(
0,
1/
#125
1#
1(
b0010 )
0-
10
#126
b1111 '
0(
1,
#127
1(
b0011 )
1-
#128
0#
0$
0%
b0100 &
b0000 '
0(
b0100 )
0*
0+
0,
0-
0.
0/
00
11
02
13
05
#129
1(
b0101 )
1-
#130
b0001 '
0(
1,
#131
1#
1(
b0110 )
0-
10
#132
0#
b0010 '
0(
0,
1/
#133
1(
b0111 )
1-
#134
b0011 '
0(
1,
#135
1#
1$
1%
1(
b1000 )
0-
00
03
16
#136
0#
0$
b0100 '
0(
0,
0/
12
#137
1(
b1001 )
1-
#138
b0101 '
0(
1,
#139
1#
1(
b1010 )
0-
10
#140
0#
b0110 '
0(
0,
1/
#141
1(
b1011 )
1-
#142
b0111 '
0(
1,
#143
1#
1$
1(
b1100 )
0-
00
13
#144
0#
0$
0%
b1000 '
0(
0,
0/
02
15
#145
1(
b1101 )
1-
#146
b1001 '
0(
1,
#147
1#
1(
b1110 )
0-
10
#148
0#
b1010 '
0(
0,
1/
#149
1(
b1111 )
1-
#150
b1011 '
0(
1,
#151
1#
1$
1%
1(
b0000 )
1*
0-
00
03
06
#152
0#
0$
b1100 '
0(
0,
0/
12
#153
1(
b0001 )
1-
#154
b1101 '
0(
1,
#155
1#
1(
b0010 )
0-
10
#156
0#
b1110 '
0(
0,
1/
#157
1(
b0011 )
1-
#158
b1111 '
0(
1,
#159
1#
1$
1(
b0100 )
0-
00
13
#160
0#
0$
0%
b0101 &
b0000 '
0(
b0101 )
0*
1+
0,
1-
0/
02
05
#161
1#
1(
b0110 )
0-
10
#162
b0001 '
0(
1,
#163
1(
b0111 )
1-
#164
0#
b0010 '
0(
0,
1/
#165
1#
1$
1%
1(
b1000 )
0-
00
03
16
#166
b0011 '
0(
1,
#167
1(
b1001 )
1-
#168
0#
0$
b0100 '
0(
0,
0/
12
#169
1#
1(
b1010 )
0-
10
#170
b0101 '
0(
1,
#171
1(
b1011 )
1-
#172
0#
b0110 '
0(
0,
1/
#173
1#
1$
1(
b1100 )
0-
00
13
#174
b0111 '
0(
1,
#175
1(
b1101 )
1-
#176
0#
0$
0%
b1000 '
0(
0,
0/
02
15
#177
1#
1(
b1110 )
0-
10
#178
b1001 '
0(
1,
#179
1(
b1111 )
1-
#180
0#
b1010 '
0(
0,
1/
#181
1#
1$
1%
1(
b0000 )
1*
0-
00
03
06
#182
b1011 '
0(
1,
#183
1(
b0001 )
1-
#184
0#
0$
b1100 '
0(
0,
0/
12
#185
1#
1(
b0010 )
0-
10
#186
b1101 '
0(
1,
#187
1(
b0011 )
1-
#188
0#
b1110 '
0(
0,
1/
#189
1#
1$
1(
b0100 )
0-
00
13
#190
b1111 '
0(
1,
#191
1(
b0101 )
1-
#192
0#
0$
0%
b0110 &
b0000 '
0(
b0110 )
0*
0+
0,
0-
1.
0/
10
02
05
#193
1(
b0111 )
1-
#194
b0001 '
0(
1,
#195
1#
1$
1%
1(
b1000 )
0-
00
03
16
#196
0#
b0010 '
0(
0,
1/
#197
1(
b1001 )
1-
#198
b0011 '
0(
1,
#199
1#
1(
b1010 )
0-
10
#200
0#
0$
b0100 '
0(
0,
0/
12
#201
1(
b1011 )
1-
#202
b0101 '
0(
1,
#203
1#
1$
1(
b1100 )
0-
00
13
#204
0#
b0110 '
0(
0,
1/
#205
1(
b1101 )
1-
#206
b0111 '
0(
1,
#207
1#
1(
b1110 )
0-
10
#208
0#
0$
0%
b1000 '
0(
0,
0/
02
15
#209
1(
b1111 )
1-
#210
b1001 '
0(
1,
#211
1#
1$
1%
1(
b0000 )
1*
0-
00
03
06
#212
0#
b1010 '
0(
0,
1/
#213
1(
b0001 )
1-
#214
b1011 '
0(
1,
#215
1#
1(
b0010 )
0-
10
#216
0#
0$
b1100 '
0(
0,
0/
12
#217
1(
b0011 )
1-
#218
b1101 '
0(
1,
#219
1#
1$
1(
b0100 )
0-
00
13
#220
0#
b1110 '
0(
0,
1/
#221
1(
b0101 )
1-
#222
b1111 '
0(
1,
#223
1#
1(
b0110 )
0-
10
#224
0#
0$
0%
b0111 &
b0000 '
0(
b0111 )
0*
1+
0,
1-
0/
02
05
#225
1#
1$
1%
1(
b1000 )
0-
00
03
16
#226
b0001 '
0(
1,
#227
1(
b1001 )
1-
#228
0#
b0010 '
0(
0,
1/
#229
1#
1(
b1010 )
0-
10
#230
b0011 '
0(
1,
#231
1(
b1011 )
1-
#232
0#
0$
b0100 '
0(
0,
0/
12
#233
1#
1$
1(
b1100 )
0-
00
13
#234
b0101 '
0(
1,
#235
1(
b1101 )
1-
#236
0#
b0110 '
0(
0,
1/
#237
1#
1(
b1110 )
0-
10
#238
b0111 '
0(
1,
#239
1(
b1111 )
1-
#240
0#
0$
0%
b1000 '
0(
0,
0/
02
15
#241
1#
1$
1%
1(
b0000 )
1*
0-
00
03
06
#242
b1001 '
0(
1,
#243
1(
b0001 )
1-
#244
0#
b1010 '
0(
0,
1/
#245
1#
1(
b0010 )
0-
10
#246
b1011 '
0(
1,
#247
1(
b0011 )
1-
#248
0#
0$
b1100 '
0(
0,
0/
12
#249
1#
1$
1(
b0100 )
0-
00
13
#250
b1101 '
0(
1,
#251
1(
b0101 )
1-
#252
0#
b1110 '
0(
0,
1/
#253
1#
1(
b0110 )
0-
10
#254
b1111 '
0(
1,
#255
1(
b0111 )
1-
#256
0#
0$
0%
b1000 &
b0000 '
0(
b1000 )
0*
0+
0,
0-
0.
0/
00
01
02
03
14
05
16
#257
1(
b1001 )
1-
#258
b0001 '
0(
1,
#259
1#
1(
b1010 )
0-
10
#260
0#
b0010 '
0(
0,
1/
#261
1(
b1011 )
1-
#262
b0011 '
0(
1,
#263
1#
1$
1(
b1100 )
0-
00
13
#264
0#
0$
b0100 '
0(
0,
0/
12
#265
1(
b1101 )
1-
#266
b0101 '
0(
1,
#267
1#
1(
b1110 )
0-
10
#268
0#
b0110 '
0(
0,
1/
#269
1(
b1111 )
1-
#270
b0111 '
0(
1,
#271
1#
1$
1%
1(
b0000 )
1*
0-
00
03
06
#272
0#
0$
0%
b1000 '
0(
0,
0/
02
15
#273
1(
b0001 )
1-
#274
b1001 '
0(
1,
#275
1#
1(
b0010 )
0-
10
#276
0#
b1010 '
0(
0,
1/
#277
1(
b0011 )
1-
#278
b1011 '
0(
1,
#279
1#
1$
1(
b0100 )
0-
00
13
#280
0#
0$
b1100 '
0(
0,
0/
12
#281
1(
b0101 )
1-
#282
b1101 '
0(
1,
#283
1#
1(
b0110 )
0-
10
#284
0#
b1110 '
0(
0,
1/
#285
1(
b0111 )
1-
#286
b1111 '
0(
1,
#287
1#
1$
1%
1(
b1000 )
0-
00
03
16
#288
0#
0$
0%
b1001 &
b0000 '
0(
b1001 )
0*
1+
0,
1-
0/
02
05
#289
1#
1(
b1010 )
0-
10
#290
b0001 '
0(
1,
#291
1(
b1011 )
1-
#292
0#
b0010 '
0(
0,
1/
#293
1#
1$
1(
b1100 )
0-
00
13
#294
b0011 '
0(
1,
#295
1(
b1101 )
1-
#296
0#
0$
b0100 '
0(
0,
0/
12
#297
1#
1(
b1110 )
0-
10
#298
b0101 '
0(
1,
#299
1(
b1111 )
1-
#300
0#
b0110 '
0(
0,
1/
#301
1#
1$
1%
1(
b0000 )
1*
0-
00
03
06
#302
b0111 '
0(
1,
#303
1(
b0001 )
1-
#304
0#
0$
0%
b1000 '
0(
0,
0/
02
15
#305
1#
1(
b0010 )
0-
10
#306
b1001 '
0(
1,
#307
1(
b0011 )
1-
#308
0#
b1010 '
0(
0,
1/
#309
1#
1$
1(
b0100 )
0-
00
13
#310
b1011 '
0(
1,
#311
1(
b0101 )
1-
#312
0#
0$
b1100 '
0(
0,
0/
12
#313
1#
1(
b0110 )
0-
10
#314
b1101 '
0(
1,
#315
1(
b0111 )
1-
#316
0#
b1110 '
0(
0,
1/
#317
1#
1$
1%
1(
b1000 )
0-
00
03
16
#318
b1111 '
0(
1,
#319
1(
b1001 )
1-
#320
0#
0$
0%
b1010 &
b0000 '
0(
b1010 )
0*
0+
0,
0-
1.
0/
10
02
05
#321
1(
b1011 )
1-
#322
b0001 '
0(
1,
#323
1#
1$
1(
b1100 )
0-
00
13
#324
0#
b0010 '
0(
0,
1/
#325
1(
b1101 )
1-
#326
b0011 '
0(
1,
#327
1#
1(
b1110 )
0-
10
#328
0#
0$
b0100 '
0(
0,
0/
12
#329
1(
b1111 )
1-
#330
b0101 '
0(
1,
#331
1#
1$
1%
1(
b0000 )
1*
0-
00
03
06
#332
0#
b0110 '
0(
0,
1/
#333
1(
b0001 )
1-
#334
b0111 '
0(
1,
#335
1#
1(
b0010 )
0-
10
#336
0#
0$
0%
b1000 '
0(
0,
0/
02
15
#337
1(
b0011 )
1-
#338
b1001 '
0(
1,
#339
1#
1$
1(
b0100 )
0-
00
13
#340
0#
b1010 '
0(
0,
1/
#341
1(
b0101 )
1-
#342
b1011 '
0(
1,
#343
1#
1(
b0110 )
0-
10
#344
0#
0$
b1100 '
0(
0,
0/
12
#345
1(
b0111 )
1-
#346
b1101 '
0(
1,
#347
1#
1$
1%
1(
b1000 )
0-
00
03
16
#348
0#
b1110 '
0(
0,
1/
#349
1(
b1001 )
1-
#350
b1111 '
0(
1,
#351
1#
1(
b1010 )
0-
10
#352
0#
0$
0%
b1011 &
b0000 '
0(
b1011 )
0*
1+
0,
1-
0/
02
05
#353
1#
1$
1(
b1100 )
0-
00
13
#354
b0001 '
0(
1,
#355
1(
b1101 )
1-
#356
0#
b0010 '
0(
0,
1/
#357
1#
1(
b1110 )
0-
10
#358
b0011 '
0(
1,
#359
1(
b1111 )
1-
#360
0#
0$
b0100 '
0(
0,
0/
12
#361
1#
1$
1%
1(
b0000 )
1*
0-
00
03
06
#362
b0101 '
0(
1,
#363
1(
b0001 )
1-
#364
0#
b0110 '
0(
0,
1/
#365
1#
1(
b0010 )
0-
10
#366
b0111 '
0(
1,
#367
1(
b0011 )
1-
#368
0#
0$
0%
b1000 '
0(
0,
0/
02
15
#369
1#
1$
1(
b0100 )
0-
00
13
#370
b1001 '
0(
1,
#371
1(
b0101 )
1-
#372
0#
b1010 '
0(
0,
1/
#373
1#
1(
b0110 )
0-
10
#374
b1011 '
0(
1,
#375
1(
b0111 )
1-
#376
0#
0$
b1100 '
0(
0,
0/
12
#377
1#
1$
1%
1(
b1000 )
0-
00
03
16
#378
b1101 '
0(
1,
#379
1(
b1001 )
1-
#380
0#
b1110 '
0(
0,
1/
#381
1#
1(
b1010 )
0-
10
#382
b1111 '
0(
1,
#383
1(
b1011 )
1-
#384
0#
0$
0%
b1100 &
b0000 '
0(
b1100 )
0*
0+
0,
0-
0.
0/
00
11
02
13
05
#385
1(
b1101 )
1-
#386
b0001 '
0(
1,
#387
1#
1(
b1110 )
0-
10
#388
0#
b0010 '
0(
0,
1/
#389
1(
b1111 )
1-
#390
b0011 '
0(
1,
#391
1#
1$
1%
1(
b0000 )
1*
0-
00
03
06
#392
0#
0$
b0100 '
0(
0,
0/
12
#393
1(
b0001 )
1-
#394
b0101 '
0(
1,
#395
1#
1(
b0010 )
0-
10
#396
0#
b0110 '
0(
0,
1/
#397
1(
b0011 )
1-
#398
b0111 '
0(
1,
#399
1#
1$
1(
b0100 )
0-
00
13
#400
0#
0$
0%
b1000 '
0(
0,
0/
02
15
#401
1(
b0101 )
1-
#402
b1001 '
0(
1,
#403
1#
1(
b0110 )
0-
10
#404
0#
b1010 '
0(
0,
1/
#405
1(
b0111 )
1-
#406
b1011 '
0(
1,
#407
1#
1$
1%
1(
b1000 )
0-
00
03
16
#408
0#
0$
b1100 '
0(
0,
0/
12
#409
1(
b1001 )
1-
#410
b1101 '
0(
1,
#411
1#
1(
b1010 )
0-
10
#412
0#
b1110 '
0(
0,
1/
#413
1(
b1011 )
1-
#414
b1111 '
0(
1,
#415
1#
1$
1(
b1100 )
0-
00
13
#416
0#
0$
0%
b1101 &
b0000 '
0(
b1101 )
0*
1+
0,
1-
0/
02
05
#417
1#
1(
b1110 )
0-
10
#418
b0001 '
0(
1,
#419
1(
b1111 )
1-
#420
0#
b0010 '
0(
0,
1/
#421
1#
1$
1%
1(
b0000 )
1*
0-
00
03
06
#422
b0011 '
0(
1,
#423
1(
b0001 )
1-
#424
0#
0$
b0100 '
0(
0,
0/
12
#425
1#
1(
b0010 )
0-
10
#426
b0101 '
0(
1,
#427
1(
b0011 )
1-
#428
0#
b0110 '
0(
0,
1/
#429
1#
1$
1(
b0100 )
0-
00
13
#430
b0111 '
0(
1,
#431
1(
b0101 )
1-
#432
0#
0$
0%
b1000 '
0(
0,
0/
02
15
#433
1#
1(
b0110 )
0-
10
#434
b1001 '
0(
1,
#435
1(
b0111 )
1-
#436
0#
b1010 '
0(
0,
1/
#437
1#
1$
1%
1(
b1000 )
0-
00
03
16
#438
b1011 '
0(
1,
#439
1(
b1001 )
1-
#440
0#
0$
b1100 '
0(
0,
0/
12
#441
1#
1(
b1010 )
0-
10
#442
b1101 '
0(
1,
#443
1(
b1011 )
1-
#444
0#
b1110 '
0(
0,
1/
#445
1#
1$
1(
b1100 )
0-
00
13
#446
b1111 '
0(
1,
#447
1(
b1101 )
1-
#448
0#
0$
0%
b1110 &
b0000 '
0(
b1110 )
0*
0+
0,
0-
1.
0/
10
02
05
#449
1(
b1111 )
1-
#450
b0001 '
0(
1,
#451
1#
1$
1%
1(
b0000 )
1*
0-
00
03
06
#452
0#
b0010 '
0(
0,
1/
#453
1(
b0001 )
1-
#454
b0011 '
0(
1,
#455
1#
1(
b0010 )
0-
10
#456
0#
0$
b0100 '
0(
0,
0/
12
#457
1(
b0011 )
1-
#458
b0101 '
0(
1,
#459
1#
1$
1(
b0100 )
0-
00
13
#460
0#
b0110 '
0(
0,
1/
#461
1(
b0101 )
1-
#462
b0111 '
0(
1,
#463
1#
1(
b0110 )
0-
10
#464
0#
0$
0%
b1000 '
0(
0,
0/
02
15
#465
1(
b0111 )
1-
#466
b1001 '
0(
1,
#467
1#
1$
1%
1(
b1000 )
0-
00
03
16
#468
0#
b1010 '
0(
0,
1/
#469
1(
b1001 )
1-
#470
b1011 '
0(
1,
#471
1#
1(
b1010 )
0-
10
#472
0#
0$
b1100 '
0(
0,
0/
12
#473
1(
b1011 )
1-
#474
b1101 '
0(
1,
#475
1#
1$
1(
b1100 )
0-
00
13
#476
0#
b1110 '
0(
0,
1/
#477
1(
b1101 )
1-
#478
b1111 '
0(
1,
#479
1#
1(
b1110 )
0-
10
#480
0#
0$
0%
b1111 &
b0000 '
0(
b1111 )
0*
1+
0,
1-
0/
02
05
#481
1#
1$
1%
1(
b0000 )
1*
0-
00
03
06
#482
b0001 '
0(
1,
#483
1(
b0001 )
1-
#484
0#
b0010 '
0(
0,
1/
#485
1#
1(
b0010 )
0-
10
#486
b0011 '
0(
1,
#487
1(
b0011 )
1-
#488
0#
0$
b0100 '
0(
0,
0/
12
#489
1#
1$
1(
b0100 )
0-
00
13
#490
b0101 '
0(
1,
#491
1(
b0101 )
1-
#492
0#
b0110 '
0(
0,
1/
#493
1#
1(
b0110 )
0-
10
#494
b0111 '
0(
1,
#495
1(
b0111 )
1-
#496
0#
0$
0%
b1000 '
0(
0,
0/
02
15
#497
1#
1$
1%
1(
b1000 )
0-
00
03
16
#498
b1001 '
0(
1,
#499
1(
b1001 )
1-
#500
0#
b1010 '
0(
0,
1/
#501
1#
1(
b1010 )
0-
10
#502
b1011 '
0(
1,
#503
1(
b1011 )
1-
#504
0#
0$
b1100 '
0(
0,
0/
12
#505
1#
1$
1(
b1100 )
0-
00
13
#506
b1101 '
0(
1,
#507
1(
b1101 )
1-
#508
0#
b1110 '
0(
0,
1/
#509
1#
1(
b1110 )
0-
10
#510
b1111 '
0(
1,
#511
1(
b1111 )
1-
